[
    {"Name":"Dikshit Khurana", "department":"RJ", "position":"Senior Executive"},
    {"Name":"Gundeep Singh", "department":"RJ", "position":"Senior Executive"},
    {"Name":"Gurneet Singh", "department":"RJ", "position":"Senior Executive"},
    {"Name":"Harpreet Kaur", "department":"RJ", "position":"Senior Executive"},
    {"Name":"Harsimran Singh", "department":"RJ", "position":"Senior Executive"},
    {"Name":"Sejal Madan", "department":"RJ", "position":"Senior Executive"},
    {"Name":"Sakshi", "department":"RJ", "position":"Senior Executive"},
    {"Name":"Shubham Savarn", "department":"RJ", "position":"Senior Executive"},
    {"Name":"Vivek Thakur", "department":"RJ", "position":"Senior Executive"},
    {"Name":"Arshpreet Singh", "department":"RJ", "position":"Senior Executive"},
    {"Name":"Divya Bhatia", "department":"RJ", "position":"Senior Executive"},
    {"Name":"Nikhil", "department":"RJ", "position":"Senior Executive"},
    {"Name":"Divya Bhatia", "department":"RJ", "position":"Senior Executive"},
    {"Name":"Arshpreet Singh", "department":"RJ", "position":"Executive"},
    {"Name":"Jasdeep Kaur Batra ", "department":"RJ", "position":"Executive"},
    {"Name":"Shashank", "department":"RJ", "position":"Executive"},
    {"Name":"Sahil Arora", "department":"RJ", "position":"Executive"},
    {"Name":"Harsh Kapoor", "department":"RJ", "position":"Executive"},
    {"Name":"Raghav Chopra", "department":"RJ", "position":"Executive"},
    {"Name":"Aayush Kalia", "department":"RJ", "position":"Executive"},
    {"Name":"Parav Khajuria", "department":"RJ", "position":"Executive"},
    {"Name":"Rupal Niranjan", "department":"RJ", "position":"Executive"},
    {"Name":"Jarawar Singh", "department":"RJ", "position":"Executive"},
    {"Name":"Astha Bhanot", "department":"RJ", "position":"Executive"},
    {"Name":"Gurnoor Kaur", "department":"RJ", "position":"Executive"},
    {"Name":"Pankaj", "department":"RJ", "position":"Executive"},

    {"Name":"Blossom", "department":"EVM", "position":"Senior Executive"},
    {"Name":"Mankirat Singh", "department":"EVM", "position":"Senior Executive"},
    {"Name":"Abhishek", "department":"EVM", "position":"Executive"},
    {"Name":"Anmol Singh", "department":"EVM", "position":"Executive"},
    {"Name":"Arshdeep Kaur", "department":"EVM", "position":"Executive"},
    {"Name":"Dikshit Narayan", "department":"EVM", "position":"Executive"},
    {"Name":"Harmanpreet Kaur", "department":"EVM", "position":"Executive"},
    {"Name":"Inderpreet Singh", "department":"EVM", "position":"Executive"},
    {"Name":"Manpreet Singh", "department":"EVM", "position":"Executive"},
    {"Name":"Mehul Bedi", "department":"EVM", "position":"Executive"},
    {"Name":"Saniya Bharadwaj", "department":"EVM", "position":"Executive"},
    {"Name":"Shafneet Kaur", "department":"EVM", "position":"Executive"},

    {"Name":"Rahul Choudhary", "department":"TECH", "position":"Senior Executive"},
    {"Name":"Naunihal Singh", "department":"TECH", "position":"Sennior Executive"},
    {"Name":"Gurneet Singh", "department":"TECH", "position":"Senior Executive"},
    {"Name":"Manbir Singh", "department":"TECH", "position":"Senior Executive"},
    {"Name":"Dhruv Kumar", "department":"TECH", "position":"Senior Executive"},
    {"Name":"Rupali Devi", "department":"TECH", "position":"Senior Executive"},
    {"Name":"Ekuspreet Singh", "department":"TECH", "position":"Senior Executive"},
    {"Name":"Shashank Kumar", "department":"TECH", "position":"Senior Executive"},
    {"Name":"Ravinder Kaur", "department":"TECH", "position":"Executive"},
    {"Name":"Jayati Aggarwal", "department":"TECH", "position":"Executive"},
    {"Name":"Nitin", "department":"TECH", "position":"Executive"},
    {"Name":"Robin Rawat", "department":"TECH", "position":"Executive"},
    {"Name":"Devash Sharma", "department":"TECH", "position":"Executive"},
    {"Name":"Ranveer Singh", "department":"TECH", "position":"Executive"},
    {"Name":"Ansul Pal", "department":"TECH", "position":"Executive"},
    {"Name":"Pratham Goyal", "department":"TECH", "position":"Executive"}


    
]